ftime/__init__.py
ftime/ftime.py
ftime/test.py
ftime-1.1.dist-info/LICENSE
ftime-1.1.dist-info/METADATA
ftime-1.1.dist-info/WHEEL
ftime-1.1.dist-info/top_level.txt
ftime-1.1.dist-info/RECORD
